mytextgrid/__about__.py
mytextgrid/__init__.py
mytextgrid/eval.py
mytextgrid/core/__init__.py
mytextgrid/core/interval_tier.py
mytextgrid/core/point_tier.py
mytextgrid/core/textgrid.py
mytextgrid/core/tier.py
mytextgrid/io/__init__.py
mytextgrid/io/textgrid_in.py
mytextgrid/io/textgrid_out.py
mytextgrid/io/parser/__init__.py
mytextgrid/io/parser/fulltext_format.py
mytextgrid/io/templates/long_format.TextGrid.jinja
mytextgrid/io/templates/short_format.TextGrid.jinja
mytextgrid-0.9.0.dist-info/METADATA
mytextgrid-0.9.0.dist-info/WHEEL
mytextgrid-0.9.0.dist-info/licenses/LICENSE
mytextgrid-0.9.0.dist-info/RECORD
