Metadata-Version: 2.4
Name: mytextgrid
Version: 0.9.0
Summary: Create, read, modify and query TextGrid files.
Project-URL: Documentation, https://mytextgrid.readthedocs.io/en/latest/index.html
Project-URL: Issues, https://github.com/rolandomunoz/mytextGrid/issues
Project-URL: Source, https://github.com/rolandomunoz/mytextgrid
Author-email: Rolando Muñoz Aramburú <rolando.muar@gmail.com>
License-File: LICENSE
Keywords: TextGrid,praat
Classifier: Intended Audience :: Developers
Classifier: License :: OSI Approved :: GNU General Public License v3 (GPLv3)
Classifier: Operating System :: OS Independent
Classifier: Programming Language :: Python :: 3
Classifier: Topic :: Text Processing :: Linguistic
Requires-Python: >=3.7
Requires-Dist: chardet>=5.0.0
Requires-Dist: jinja2>=3.1.2
Requires-Dist: markupsafe>=2.1.1
